[
  {
  "id": 1,
  "nombre": "Salomo",
  "apellido": "Stair",
  "email": "sstair0@yellowpages.com",
  "password": "xo2xNkB",
  "tipo": "user",
  "imagen": "/images/users/user_1.png"
}, {
  "id": 2,
  "nombre": "Brittney",
  "apellido": "Davidi",
  "email": "bdavidi1@dion.ne.jp",
  "password": "9W86JCJwdWE",
  "tipo": "admin",
  "imagen": "/images/users/user_2.png"
}, {
  "id": 3,
  "nombre": "Arlin",
  "apellido": "Skoughman",
  "email": "askoughman2@imdb.com",
  "password": "S8HDdZ5PFqO",
  "tipo": "user",
  "imagen": "/images/users/user_3.png"
}, {
  "id": 4,
  "nombre": "Silvain",
  "apellido": "Bogaert",
  "email": "sbogaert3@microsoft.com",
  "password": "lHN67HTI",
  "tipo": "user",
  "imagen": "/images/users/user_4.png"
}, {
  "id": 5,
  "nombre": "Paulie",
  "apellido": "Edgehill",
  "email": "pedgehill4@tuttocitta.it",
  "password": "hmvl2HM6",
  "tipo": "user",
  "imagen": "/images/users/user_5.png"
}, {
  "id": 6,
  "nombre": "Ax",
  "apellido": "Wigfall",
  "email": "awigfall5@kickstarter.com",
  "password": "OPQMR9h",
  "tipo": "user",
  "imagen": "/images/users/user_6.png"
}, {
  "id": 7,
  "nombre": "Ad",
  "apellido": "Sibthorpe",
  "email": "asibthorpe6@hatena.ne.jp",
  "password": "M7VXFad",
  "tipo": "user",
  "imagen": "/images/users/user_7.png"
}, {
  "id": 8,
  "nombre": "Kakalina",
  "apellido": "Werny",
  "email": "kwerny7@stumbleupon.com",
  "password": "auARsMtWJun",
  "tipo": "user",
  "imagen": "/images/users/user_8.png"
}, {
  "id": 9,
  "nombre": "Jeannette",
  "apellido": "Gerriet",
  "email": "jgerriet8@ow.ly",
  "password": "72Rdly2Fs",
  "tipo": "user",
  "imagen": "/images/users/user_8.png"
}, {
  "id": 10,
  "nombre": "Willard",
  "apellido": "Hand",
  "email": "whand9@reuters.com",
  "password": "W34bB7",
  "tipo": "user",
  "imagen": "/images/users/user_4.png"
}, {
  "id": 11,
  "nombre": "Elana",
  "apellido": "Ravens",
  "email": "eravensa@typepad.com",
  "password": "gj1cZxy",
  "tipo": "user",
  "imagen": "/images/users/user_2.png"
}, {
  "id": 12,
  "nombre": "Haslett",
  "apellido": "Mynott",
  "email": "hmynottb@comsenz.com",
  "password": "1ajziSN3J6Iu",
  "tipo": "user",
  "imagen": "/images/users/user_1.png"
}, {
  "id": 13,
  "nombre": "Cheston",
  "apellido": "Alejandri",
  "email": "calejandric@hhs.gov",
  "password": "qtkd5nCcP",
  "tipo": "user",
  "imagen": "/images/users/user_5.png"
}, {
  "id": 14,
  "nombre": "Monique",
  "apellido": "Skakunas",
  "email": "mskakunasd@hubpages.com",
  "password": "cG35pyyLkTqc",
  "tipo": "user",
  "imagen": "/images/users/user_3.png"
}, {
  "id": 15,
  "nombre": "Vicky",
  "apellido": "Liff",
  "email": "vliffe@shop-pro.jp",
  "password": "QI7kAsKBs1S",
  "tipo": "user",
  "imagen": "/images/users/user_7.png"
}, {
  "id": 16,
  "nombre": "Kennan",
  "apellido": "Edy",
  "email": "kedyf@biglobe.ne.jp",
  "password": "E446g1UiK",
  "tipo": "user",
  "imagen": "/images/users/user_2.png"
}, {
  "id": 17,
  "nombre": "Lindon",
  "apellido": "Warrener",
  "email": "lwarrenerg@netscape.com",
  "password": "fYIMi1cyGuX",
  "tipo": "user",
  "imagen": "/images/users/user_1.png"
}, {
  "id": 18,
  "nombre": "Sigismond",
  "apellido": "Paulusch",
  "email": "spauluschh@xinhuanet.com",
  "password": "xuIeR7SDIy",
  "tipo": "user",
  "imagen": "/images/users/user_8.png"
}, {
  "id": 19,
  "nombre": "Lorette",
  "apellido": "O'Reilly",
  "email": "loreillyi@dailymail.co.uk",
  "password": "NJbPHLv",
  "tipo": "user",
  "imagen": "/images/users/user_4.png"
}, {
  "id": 20,
  "nombre": "Antonia",
  "apellido": "Delagnes",
  "email": "adelagnesj@hugedomains.com",
  "password": "LABqWG",
  "tipo": "user",
  "imagen": "/images/users/user_3.png"
},
{
  "id": 21,
  "nombre": "Valeria",
  "apellido": "Muñoz",
  "email": "valeria.munoz@hotmail.com",
  "password": "Animales123",
  "tipo": "admin",
  "imagen": "/images/users/user_6.png"
}
]